invisibleroads_macros_geometry/__init__.py
invisibleroads_macros_geometry-1.0.0.dist-info/METADATA
invisibleroads_macros_geometry-1.0.0.dist-info/WHEEL
invisibleroads_macros_geometry-1.0.0.dist-info/entry_points.txt
invisibleroads_macros_geometry-1.0.0.dist-info/top_level.txt
invisibleroads_macros_geometry-1.0.0.dist-info/zip-safe
invisibleroads_macros_geometry-1.0.0.dist-info/RECORD
