Metadata-Version: 2.1
Name: invisibleroads-macros-geometry
Version: 1.0.0
Summary: Shortcut functions for geometry operations
Home-page: https://github.com/invisibleroads/invisibleroads-macros-geometry
Author: Roy Hyunjin Han
Author-email: rhh@crosscompute.com
License: UNKNOWN
Keywords: invisibleroads
Platform: UNKNOWN
Classifier: Programming Language :: Python
Classifier: License :: OSI Approved :: MIT License
Provides-Extra: test
Requires-Dist: pytest ; extra == 'test'
Requires-Dist: pytest-cov ; extra == 'test'
Requires-Dist: shapely ; extra == 'test'
